docs/.DS_Store
docs/Makefile
docs/SP500.csv
docs/changelog.md
docs/conduct.md
docs/conf.py
docs/contributing.md
docs/example.ipynb
docs/index.md
docs/make.bat
docs/requirements.txt
src/project/CHANGELOG.md
src/project/__init__.py
src/project/custom_backtest.py
src/project/dashboard.py
src/project/work.py
pybacktestchain_extensions-1.1.1.dist-info/LICENSE
pybacktestchain_extensions-1.1.1.dist-info/METADATA
pybacktestchain_extensions-1.1.1.dist-info/WHEEL
pybacktestchain_extensions-1.1.1.dist-info/RECORD
