Metadata-Version: 2.3
Name: pybacktestchain-extensions
Version: 1.1.1
Summary: Python Project, M2 203
License: MIT
Author: Maxime Lorenzo
Requires-Python: >=3.10,<4.0
Classifier: License :: OSI Approved :: MIT License
Classifier: Programming Language :: Python :: 3
Classifier: Programming Language :: Python :: 3.10
Classifier: Programming Language :: Python :: 3.11
Classifier: Programming Language :: Python :: 3.12
Classifier: Programming Language :: Python :: 3.13
Requires-Dist: numba (>=0.60.0,<0.61.0)
Requires-Dist: pybacktestchain (>=0.2.1,<0.3.0)
Requires-Dist: streamlit (>=1.41.1,<2.0.0)
